rat_engine/__init__.py
rat_engine/__pycache__/__init__.cpython-311.pyc
rat_engine/__pycache__/cache_config.cpython-311.pyc
rat_engine/__pycache__/error_handling.cpython-311.pyc
rat_engine/__pycache__/grpc_decorators.cpython-311.pyc
rat_engine/__pycache__/quickmem.cpython-311.pyc
rat_engine/__pycache__/security.cpython-311.pyc
rat_engine/__pycache__/templates.cpython-311.pyc
rat_engine/__pycache__/web_app.cpython-311.pyc
rat_engine/_rat_engine.cpython-311-darwin.so
rat_engine/app_manager.py
rat_engine/cache_config.py
rat_engine/cli.py
rat_engine/enhanced_cli.py
rat_engine/error_handling.py
rat_engine/grpc_decorators.py
rat_engine/quickmem.py
rat_engine/security.py
rat_engine/templates.py
rat_engine/web_app.py
rat_engine/web_app.py.backup
rat_engine_py-1.0.6.dist-info/METADATA
rat_engine_py-1.0.6.dist-info/WHEEL
rat_engine_py-1.0.6.dist-info/RECORD
