Metadata-Version: 2.4
Name: rat-engine-py
Version: 1.0.6
Classifier: Development Status :: 5 - Production/Stable
Classifier: Intended Audience :: Developers
Classifier: License :: OSI Approved :: GNU Lesser General Public License v3 (LGPLv3)
Classifier: Programming Language :: Rust
Classifier: Programming Language :: Python :: Implementation :: CPython
Classifier: Programming Language :: Python :: 3
Classifier: Programming Language :: Python :: 3.11
Classifier: Programming Language :: Python :: 3.12
Classifier: Topic :: Internet :: WWW/HTTP :: HTTP Servers
Classifier: Topic :: Internet :: WWW/HTTP :: Dynamic Content
Classifier: Topic :: Software Development :: Libraries :: Python Modules
Classifier: Topic :: Software Development :: Libraries :: Application Frameworks
Classifier: Operating System :: OS Independent
Summary: Python bindings for RAT Engine - 高性能HTTP服务器引擎，提供Flask风格的API和自动硬件优化功能
Keywords: http,server,web,async,performance,flask,grpc,rust,high-performance
Author-email: 0ldm0s <oldmos@gmail.com>
Requires-Python: >=3.11
Project-URL: Homepage, https://github.com/0ldm0s/rat_engine
Project-URL: Repository, https://github.com/0ldm0s/rat_engine
Project-URL: Documentation, https://docs.rs/rat_engine/latest/rat_engine/
Project-URL: Bug Tracker, https://github.com/0ldm0s/rat_engine/issues
